[
	{
		"review": "유이나 예뻐서....10점",
		"date": "17.11.17",
		"rating": "10",
		"author": "wooc****",
		"review_id": "13399002",
		"movie_id": "159735"
	},
	{
		"review": "전편의 떡밥을 잘회수하는 편이였구요 학생인신분인 제가 봐도  이해를 할수있을정도의 난이도인 철학적인 내용, 적당한 생각을  영화보고 나서 할수있게끔 하는 영화였네요 전편은 돈아깝다는 생각이 드는 일본 특유 요소들이 ...",
		"date": "17.11.08",
		"rating": "9",
		"author": "rlaw****",
		"review_id": "13371217",
		"movie_id": "159735"
	},
	{
		"review": "후편도 재밌음 . 이런 청춘물 좋다",
		"date": "17.12.01",
		"rating": "10",
		"author": "dydg****",
		"review_id": "13447417",
		"movie_id": "159735"
	},
	{
		"review": "한국개봉 했엇다니 ㅋㅋ",
		"date": "19.03.29",
		"rating": "10",
		"author": "17to****",
		"review_id": "15463038",
		"movie_id": "159735"
	},
	{
		"review": "가능성없는 하나시다...",
		"date": "18.06.28",
		"rating": "10",
		"author": "lkm3****",
		"review_id": "14250437",
		"movie_id": "159735"
	},
	{
		"review": "그래그래 유이나가 이뻐서 10점 줄께 그 외에 젠장 노잼이다",
		"date": "18.01.27",
		"rating": "10",
		"author": "kuri****",
		"review_id": "13710437",
		"movie_id": "159735"
	},
	{
		"review": "일본 영화중에 제일 괜찮았다",
		"date": "18.01.19",
		"rating": "10",
		"author": "qo78****",
		"review_id": "13680307",
		"movie_id": "159735"
	},
	{
		"review": "당신의 췌장을 먹고싶다 도 그렇지만 라노벨은 애니화 하지 않는이상 실물 영화는 망한다.(원작과 갭이 너무 크다)유일하게 은혼?이 그나마 성공했지...목소리의 형태도 봐봐라 실사판보다 애니가 더 인기 있었지.",
		"date": "17.11.03",
		"rating": "4",
		"author": "0119****",
		"review_id": "13357999",
		"movie_id": "159735"
	},
	{
		"review": "불쌍해서 10점준다. 관객수가 10명이 뭐냐. ㅉㅉ",
		"date": "17.11.03",
		"rating": "10",
		"author": "yumu****",
		"review_id": "13356440",
		"movie_id": "159735"
	},
	{
		"review": "도널프 트럼프 저새낀 애니영화만 보면 오타크들이 몰려논 거품평점 방지용 이  ㅈㄹ 함 ㅋㅋ",
		"date": "17.11.10",
		"rating": "1",
		"author": "snlk****",
		"review_id": "13378842",
		"movie_id": "159735"
	},
	{
		"review": "오타쿠들이 올려논 거품평점 방지용",
		"date": "17.11.05",
		"rating": "1",
		"author": "Donald J Trump(mjh5****",
		"review_id": "13362010",
		"movie_id": "159735"
	},
	{
		"review": "펴어엉저어엄1위이이바앙지이요옹",
		"date": "17.11.03",
		"rating": "1",
		"author": "kys0****",
		"review_id": "13357117",
		"movie_id": "159735"
	}
]