[
	{
		"review": "배우들부터 심각하다..",
		"date": "17.12.26",
		"rating": "1",
		"author": "yoon****",
		"review_id": "13555026",
		"movie_id": "165588"
	},
	{
		"review": "이것도 영화라고..  할말이 없다.",
		"date": "18.04.18",
		"rating": "1",
		"author": "chch****",
		"review_id": "14019147",
		"movie_id": "165588"
	},
	{
		"review": "제목하고 내용하고 아무 상관 없네...ㅋㅋ",
		"date": "19.07.30",
		"rating": "2",
		"author": "adiv****",
		"review_id": "15957171",
		"movie_id": "165588"
	},
	{
		"review": "이거 안볼란다 ㅋㅋ 배우하는인간들 하네 신선배우가 그렇게도 없나 해외영화 동상가들 이나 봐야겠다 ㅋㅋ",
		"date": "18.01.23",
		"rating": "1",
		"author": "maxx****",
		"review_id": "13698252",
		"movie_id": "165588"
	},
	{
		"review": "이번에도 똑같은 배우들이네 안 볼렵니다",
		"date": "17.12.23",
		"rating": "1",
		"author": "jina****",
		"review_id": "13526837",
		"movie_id": "165588"
	},
	{
		"review": "번져 버린 화장 같은 영화.",
		"date": "18.07.12",
		"rating": "3",
		"author": "dlwo****",
		"review_id": "14299198",
		"movie_id": "165588"
	},
	{
		"review": "이감독 진짜 영화 찍으면 대박 날듯 그런데 이슬? 아무튼 연출, 스토리 대박임",
		"date": "18.01.02",
		"rating": "10",
		"author": "ocru****",
		"review_id": "13601284",
		"movie_id": "165588"
	},
	{
		"review": "이감독은 연출 스토리가 꽤나 좋다",
		"date": "17.12.25",
		"rating": "10",
		"author": "akst****",
		"review_id": "13540715",
		"movie_id": "165588"
	},
	{
		"review": "간만에 화장만으로 꼴릿하게 만드는 작품이 하나 나왔네. 성인영화에서 시각적인 부분은 참 크다. 그러니깐 확 다 벗기지 좀 말고 걸치고 신고 좀 해라. 아줌마팬티 같은거는 좀 가따 버리고.. 성인영화 한다는 놈들이 은...",
		"date": "17.11.25",
		"rating": "10",
		"author": "rokm****",
		"review_id": "13426525",
		"movie_id": "165588"
	},
	{
		"review": "기대! 이번엔 제발 블러 난발 하지 말길~~",
		"date": "17.12.29",
		"rating": "9",
		"author": "hotos estin(viol****",
		"review_id": "13573665",
		"movie_id": "165588"
	}
]