[
    {
        "review": "DVD를 몇 번씩 되돌리며 보았습니다.가우디 영화제 대상을 받을 만한 충분한 이유가 느껴질 것 같습니다.감독이 전하는 메시지가 묵직하여 더 볼 생각입니다.",
        "date": "17.08.19",
        "rating": "10",
        "author": "kris****",
        "review_id": "13069015",
        "movie_id": "79264"
    },
    {
        "review": "오스카 표정 살아있네여",
        "date": "15.07.09",
        "rating": "10",
        "author": "jiso****",
        "review_id": "10082225",
        "movie_id": "79264"
    },
    {
        "review": "극중 밴드 Trash음악에 5점,,영화는 제목그대로 쓰레기",
        "date": "13.04.28",
        "rating": "5",
        "author": "kjc7****",
        "review_id": "7490538",
        "movie_id": "79264"
    },
    {
        "review": "메세지가 뭔지?",
        "date": "12.11.16",
        "rating": "5",
        "author": "겨울산행(yht0****)",
        "review_id": "6892875",
        "movie_id": "79264"
    },
    {
        "review": "잘만든영화",
        "date": "12.08.18",
        "rating": "10",
        "author": "마리안로드(knig****)",
        "review_id": "6621691",
        "movie_id": "79264"
    },
    {
        "review": "영상 음악 주인공 스타일까지는 좋은데 내용은 영 -_-  도대체 왜 그리 책임감없게 바람을 피나;; 그에대한 설득력 전혀없고.... 죄책감 전혀 없고 .... 위험한 정사가 아니고 책임감없는 정사라고 하자 위험하리만치 괜찮은 정사장면도 변변치않고",
        "date": "12.08.18",
        "rating": "2",
        "author": "달리(pape****)",
        "review_id": "6620122",
        "movie_id": "79264"
    },
    {
        "review": "재미 없어..보지마!!",
        "date": "12.07.01",
        "rating": "1",
        "author": "yang****",
        "review_id": "6437474",
        "movie_id": "79264"
    },
    {
        "review": "밴드 음악 너무 좋아요~",
        "date": "11.06.03",
        "rating": "10",
        "author": "hell****",
        "review_id": "5462317",
        "movie_id": "79264"
    },
    {
        "review": "진리다",
        "date": "10.12.31",
        "rating": "10",
        "author": "lcm2****",
        "review_id": "5108036",
        "movie_id": "79264"
    },
    {
        "review": "그렇겐안되지",
        "date": "10.12.25",
        "rating": "1",
        "author": "pa14****",
        "review_id": "5085262",
        "movie_id": "79264"
    },
    {
        "review": "콜",
        "date": "10.12.25",
        "rating": "10",
        "author": "bsy9****",
        "review_id": "5084605",
        "movie_id": "79264"
    },
    {
        "review": "만점영화만들자",
        "date": "10.12.25",
        "rating": "10",
        "author": "zzzm****",
        "review_id": "5083788",
        "movie_id": "79264"
    }
]