[
	{
		"review": "스톱모션 좋아해서 자주 찾아보는데 스톱모션 다운 스토리와 연출 이여서 전 재밌게 봤습니다^^ 진지하게 보려고 하면 이해 안되고 지루하겠지만 특유의 엉뚱하고 동화적인 요소를 고려해서 본다면 소재도 그렇고 잘 만든 작품...",
		"date": "21.04.22",
		"rating": "10",
		"author": "nana****",
		"review_id": "17485657",
		"movie_id": "175878"
	},
	{
		"review": "어렸을 때 좋아하던 스톱 애니메이션이라고 해서 봤다. 시간과 공을 무지 들였더라. 수상도 엄청 많은거 보니 나름 인정받은 작품이라 생각한다. 그 노력을 생각해서라도 무작정 까대기하지는 하지 말기를 하는 바램이다.",
		"date": "20.06.15",
		"rating": "10",
		"author": "illu****",
		"review_id": "16908964",
		"movie_id": "175878"
	},
	{
		"review": "진짜 재미없었고 지루했어요..5살짜리동생도 이거보고 재미없다고 징징댔어요..",
		"date": "19.11.17",
		"rating": "1",
		"author": "dhf0****",
		"review_id": "16407422",
		"movie_id": "175878"
	},
	{
		"review": "이게 영화임?",
		"date": "19.11.16",
		"rating": "1",
		"author": "gant****",
		"review_id": "16403939",
		"movie_id": "175878"
	},
	{
		"review": "WILD(gant****) 진짜 한심한 자식이다.  그럼 영화지. 왜 애니메이션 기법을 사용해 만든 영상은 영화가 아니냐?",
		"date": "19.11.16",
		"rating": "10",
		"author": "idea****",
		"review_id": "16404070",
		"movie_id": "175878"
	}
]